[
  {
    "id": 0,
    "name": "Exhibitor Company 1",
    "description": "Specializing in premium teak furniture and handcrafted home decor. loremflickr handcrafted home decor. loremflickr handcrafted home decor. loremflickr ",
    "logo": "",
    "images": [
      "https://loremflickr.com/400/300/chair?lock=11",
      "https://loremflickr.com/400/300/chair?lock=10",
      "https://loremflickr.com/400/300/chair?lock=1"
    ],
    "grade": "Platinum"
  },
  {
    "id": 1,
    "name": "Exhibitor Company 2",
    "description": "Specializing in premium teak furniture and handcrafted home decor. loremflickr handcrafted home decor. loremflickr handcrafted home decor. loremflickr ",
    "logo": "",
    "images": [
      "https://loremflickr.com/400/300/chair?lock=14",
      "https://loremflickr.com/400/300/chair?lock=13",
      "https://loremflickr.com/400/300/chair?lock=4"
    ],
    "grade": "Gold"
  },
  {
    "id": 2,
    "name": "Exhibitor Company 3",
    "description": "Specializing in premium teak furniture and handcrafted home decor. loremflickr handcrafted home decor. loremflickr handcrafted home decor. loremflickr ",
    "logo": "",
    "images": [
      "https://loremflickr.com/400/300/chair?lock=17",
      "https://loremflickr.com/400/300/chair?lock=16",
      "https://loremflickr.com/400/300/chair?lock=7"
    ],
    "grade": "Silver"
  },
  {
    "id": 3,
    "name": "Exhibitor Company 4",
    "description": "Specializing in premium teak furniture and handcrafted home decor. loremflickr handcrafted home decor. loremflickr handcrafted home decor. loremflickr ",
    "logo": "",
    "images": [
      "https://loremflickr.com/400/300/chair?lock=20",
      "https://loremflickr.com/400/300/chair?lock=19",
      "https://loremflickr.com/400/300/chair?lock=10"
    ],
    "grade": "Bronze"
  },
  {
    "id": 4,
    "name": "Exhibitor Company 5",
    "description": "Specializing in premium teak furniture and handcrafted home decor. loremflickr handcrafted home decor. loremflickr handcrafted home decor. loremflickr ",
    "logo": "",
    "images": [
      "https://loremflickr.com/400/300/chair?lock=23",
      "https://loremflickr.com/400/300/chair?lock=22",
      "https://loremflickr.com/400/300/chair?lock=13"
    ],
    "grade": "Platinum"
  },
  {
    "id": 5,
    "name": "Exhibitor Company 6",
    "description": "Specializing in premium teak furniture and handcrafted home decor. loremflickr handcrafted home decor. loremflickr handcrafted home decor. loremflickr ",
    "logo": "",
    "images": [
      "https://loremflickr.com/400/300/chair?lock=26",
      "https://loremflickr.com/400/300/chair?lock=25",
      "https://loremflickr.com/400/300/chair?lock=16"
    ],
    "grade": "Gold"
  },
  {
    "id": 6,
    "name": "Exhibitor Company 7",
    "description": "Specializing in premium teak furniture and handcrafted home decor. loremflickr handcrafted home decor. loremflickr handcrafted home decor. loremflickr ",
    "logo": "",
    "images": [
      "https://loremflickr.com/400/300/chair?lock=29",
      "https://loremflickr.com/400/300/chair?lock=28",
      "https://loremflickr.com/400/300/chair?lock=19"
    ],
    "grade": "Silver"
  },
  {
    "id": 7,
    "name": "Exhibitor Company 8",
    "description": "Specializing in premium teak furniture and handcrafted home decor. loremflickr handcrafted home decor. loremflickr handcrafted home decor. loremflickr ",
    "logo": "",
    "images": [
      "https://loremflickr.com/400/300/chair?lock=32",
      "https://loremflickr.com/400/300/chair?lock=31",
      "https://loremflickr.com/400/300/chair?lock=22"
    ],
    "grade": "Bronze"
  }
]
